CHANGES.txt
LICENSE.txt
MANIFEST.in
README.txt
buildout.cfg
setup.py
src/m01/__init__.py
src/m01.gmap.egg-info/PKG-INFO
src/m01.gmap.egg-info/SOURCES.txt
src/m01.gmap.egg-info/dependency_links.txt
src/m01.gmap.egg-info/namespace_packages.txt
src/m01.gmap.egg-info/not-zip-safe
src/m01.gmap.egg-info/requires.txt
src/m01.gmap.egg-info/top_level.txt
src/m01/gmap/README.txt
src/m01/gmap/__init__.py
src/m01/gmap/browser.py
src/m01/gmap/browser.zcml
src/m01/gmap/checker.txt
src/m01/gmap/configure.zcml
src/m01/gmap/converter.py
src/m01/gmap/interfaces.py
src/m01/gmap/schema.py
src/m01/gmap/tests.py
src/m01/gmap/util.py
src/m01/gmap/widget.py
src/m01/gmap/widget.zcml
src/m01/gmap/widget_display.pt
src/m01/gmap/widget_input.pt
src/m01/gmap/img/m01GMapWidgetIcon.png
src/m01/gmap/img/m01GMapWidgetIconShadow.png
src/m01/gmap/js/m01.gmap.v3.js